360monitoringcli-1.0.19.data/data/share/doc/360monitoring-cli/360monitoring-example.ini
360monitoringcli-1.0.19.data/data/share/doc/360monitoring-cli/LICENSE
360monitoringcli-1.0.19.data/data/share/doc/360monitoring-cli/README.md
cli360monitoring/__init__.py
cli360monitoring/monitoring.py
cli360monitoring/lib/__init__.py
cli360monitoring/lib/api.py
cli360monitoring/lib/bcolors.py
cli360monitoring/lib/config.py
cli360monitoring/lib/contacts.py
cli360monitoring/lib/functions.py
cli360monitoring/lib/incidents.py
cli360monitoring/lib/magiclinks.py
cli360monitoring/lib/nodes.py
cli360monitoring/lib/recommendations.py
cli360monitoring/lib/servercharts.py
cli360monitoring/lib/servernotifications.py
cli360monitoring/lib/servers.py
cli360monitoring/lib/sitecharts.py
cli360monitoring/lib/sitenotifications.py
cli360monitoring/lib/sites.py
cli360monitoring/lib/statistics.py
cli360monitoring/lib/usertokens.py
cli360monitoring/lib/wptoolkit.py
360monitoringcli-1.0.19.dist-info/LICENSE
360monitoringcli-1.0.19.dist-info/METADATA
360monitoringcli-1.0.19.dist-info/WHEEL
360monitoringcli-1.0.19.dist-info/entry_points.txt
360monitoringcli-1.0.19.dist-info/top_level.txt
360monitoringcli-1.0.19.dist-info/RECORD
