Metadata-Version: 2.1
Name: 360monitoringcli
Version: 1.0.19
Summary: 360 Monitoring CLI
Home-page: https://github.com/plesk/360monitoring-cli
Author: Jan Loeffler
Author-email: jan.loeffler@webpros.com
Maintainer: Jan Loeffler
Maintainer-email: jan.loeffler@webpros.com
License: MIT
Keywords: 360 system monitoring cli
Classifier: Development Status :: 5 - Production/Stable
Classifier: Environment :: Console
Classifier: Intended Audience :: System Administrators
Classifier: License :: OSI Approved :: MIT License
Classifier: Natural Language :: English
Classifier: Operating System :: POSIX :: Linux
Classifier: Operating System :: MacOS :: MacOS X
Classifier: Programming Language :: Python :: 3.4
Classifier: Programming Language :: Python :: 3.5
Classifier: Programming Language :: Python :: 3.6
Classifier: Programming Language :: Python :: 3.7
Classifier: Programming Language :: Python :: 3.8
Classifier: Programming Language :: Python :: 3.9
Classifier: Topic :: System :: Monitoring
Requires-Python: >=3.0
License-File: LICENSE
Requires-Dist: configparser
Requires-Dist: prettytable
Requires-Dist: requests
